compatibility/__init__.py
compatibility/compatibility.py
dowell_license_compatibility-0.0.1.dist-info/LICENSE
dowell_license_compatibility-0.0.1.dist-info/METADATA
dowell_license_compatibility-0.0.1.dist-info/WHEEL
dowell_license_compatibility-0.0.1.dist-info/top_level.txt
dowell_license_compatibility-0.0.1.dist-info/RECORD
