Metadata-Version: 2.1
Name: dowell-license-compatibility
Version: 0.0.1
Summary: Open Source Licence Compatibility Check Package
Home-page: UNKNOWN
Author: Marvin Okwaro
Author-email: <marvin.wekesa@gmal.com>
License: UNKNOWN
Keywords: python,License,Open Source,Compatibility
Platform: UNKNOWN
License-File: LICENSE
Requires-Dist: requests
